decimal_literal.py
decimal_literal-0.0.1.dist-info/LICENSE
decimal_literal-0.0.1.dist-info/METADATA
decimal_literal-0.0.1.dist-info/WHEEL
decimal_literal-0.0.1.dist-info/top_level.txt
decimal_literal-0.0.1.dist-info/RECORD
