Metadata-Version: 2.1
Name: decimal-literal
Version: 0.0.1
Summary: Experimental syntax for decimal literals
Home-page: https://github.com/aroberge/decimal-literal
Author: André Roberge
Author-email: Andre.Roberge@gmail.com
License: UNKNOWN
Platform: UNKNOWN
Classifier: Development Status :: 1 - Planning
Classifier: License :: OSI Approved :: MIT License
Classifier: Programming Language :: Python :: 3
Classifier: Programming Language :: Python :: 3.6
Classifier: Programming Language :: Python :: 3.7
Classifier: Programming Language :: Python :: 3.8
Classifier: Programming Language :: Python :: 3.9
Classifier: Programming Language :: Python :: 3.10
Requires-Python: >=3.6
